Project_PartB/mux2.v
module mux2 #(parameter WIDTH = 32) (
    input [WIDTH-1:0] in0,
    input [WIDTH-1:0] in1,
    input sel,
    output [WIDTH-1:0] out
);
    assign out = sel ? in1 : in0;
endmodule

Project/branchAdder.v
module branchAdder (
    input [31:0] pc,
    input [31:0] imm,
    output [31:0] pc_branch
);
    assign pc_branch = pc + (imm << 1);
endmodule

Project_PartB/immGen.v
module immGen (
    input [31:0] instr,
    output reg [31:0] imm
);
    wire [6:0] opcode = instr[6:0];
    
    always @(*) begin
        case (opcode)
            7'b0010011, 7'b0000011: // I-type (ALU immediate, Load)
                imm = {{20{instr[31]}}, instr[31:20]};
                
            7'b0100011: // S-type (Store)
                imm = {{20{instr[31]}}, instr[31:25], instr[11:7]};
                
            7'b1100011: // B-type (Branch)
                // Note: branchAdder will shift this by 1
                imm = {{20{instr[31]}}, instr[31], instr[7], instr[30:25], instr[11:8]};
                
            7'b1101111: // J-type (JAL)
                // Assuming pcAdder/branchAdder is used for JAL too, JAL branches to pc + (imm << 1)
                imm = {{12{instr[31]}}, instr[31], instr[19:12], instr[20], instr[30:21]};
                
            7'b0110111, 7'b0010111: // U-type (LUI, AUIPC)
                imm = {instr[31:12], 12'b0};
                
            default:
                imm = 32'b0;
        endcase
    end
endmodule

Project_PartA/pcAdder.v
module pcAdder (
    input [31:0] pc,
    output [31:0] pc_next_seq
);
    assign pc_next_seq = pc + 32'd4;
endmodule

Project_PartA/ProgramCounter.v
module ProgramCounter (
    input clk,
    input reset,
    input [31:0] pc_next,
    output reg [31:0] pc
);
    always @(posedge clk or posedge reset) begin
        if (reset)
            pc <= 32'b0;
        else
            pc <= pc_next;
    end
endmodule

Lab11/tb_task1.v
module tb_task1 ();
    reg clk;
    reg reset;
    reg PCSrc;
    reg [31:0] instr;
    
    wire [31:0] pc;
    wire [31:0] pc_next_seq;
    wire [31:0] pc_branch;
    wire [31:0] pc_next;
    wire [31:0] imm;
    
    // Instantiate Modules
    ProgramCounter pc_inst (
        .clk(clk),
        .reset(reset),
        .pc_next(pc_next),
        .pc(pc)
    );
    
    pcAdder pc_adder_inst (
        .pc(pc),
        .pc_next_seq(pc_next_seq)
    );
    
    immGen imm_gen_inst (
        .instr(instr),
        .imm(imm)
    );
    
    branchAdder branch_adder_inst (
        .pc(pc),
        .imm(imm),
        .pc_branch(pc_branch)
    );
    
    mux2 #(32) pc_mux (
        .in0(pc_next_seq),
        .in1(pc_branch),
        .sel(PCSrc),
        .out(pc_next)
    );
    
    // Clock generation
    always #5 clk = ~clk;
    
    initial begin
        $dumpfile("task1.vcd");
        $dumpvars(0, tb_task1);
        
        // Initialize
        clk = 0;
        reset = 1;
        PCSrc = 0;
        instr = 32'b0;
        
        #10;
        reset = 0;
        
        // Test 1: PC increment by 4
        #10; // PC becomes 4
        if (pc !== 32'd4) $display("Error: PC not 4, it is %0d", pc);
        else $display("Pass: PC incremented to 4");
        
        #10; // PC becomes 8
        if (pc !== 32'd8) $display("Error: PC not 8, it is %0d", pc);
        else $display("Pass: PC incremented to 8");
        
        // Test 2: B-Type Immediate Generation (beq x1, x2, offset)
        // offset = -8
        // immGen should output -4 (32'hFFFFFFFC)
        instr = {1'b1, 6'b111111, 5'b00010, 5'b00001, 3'b000, 4'b1100, 1'b1, 7'b1100011};
        
        #10; // PC becomes 12
        if (imm !== 32'hFFFFFFFC) $display("Error: B-Type Imm generated is %h, expected FFFFFFFC", imm);
        else $display("Pass: Correct B-Type immediate");
        
        if (pc_branch !== (pc + 32'hFFFFFFF8)) $display("Error: Branch Target is %h, expected %h", pc_branch, pc - 8);
        else $display("Pass: Correct branch target calculated (PC - 8)");
        
        // Test 3: Take Branch
        PCSrc = 1; 
        #10; // PC should now be (12 - 8) = 4
        if (pc !== 32'd4) $display("Error: PC did not branch to 4, it is %0d", pc);
        else $display("Pass: PC correctly branched to 4");
        
        // Return to sequential
        PCSrc = 0;
        #10;
        if (pc !== 32'd8) $display("Error: PC did not increment to 8 after branch, it is %0d", pc);
        else $display("Pass: PC returned to sequential execution (8)");
        
        // Test 4: Verify I-Type Immediate
        // addi x1, x0, 15
        instr = {12'd15, 5'b00000, 3'b000, 5'b00001, 7'b0010011};
        #10;
        if (imm !== 32'd15) $display("Error: I-type Immediate is %h", imm);
        else $display("Pass: Correct I-Type immediate");
        
        $display("All tests completed!");
        $finish;
    end
endmodule

Lab11/task1.vcd
$date
	Mon Mar 23 10:22:58 2026
$end
$version
	Icarus Verilog
$end
$timescale
	1s
$end
$scope module tb_task1 $end
$var wire 32 ! pc_next_seq [31:0] $end
$var wire 32 " pc_next [31:0] $end
$var wire 32 # pc_branch [31:0] $end
$var wire 32 $ pc [31:0] $end
$var wire 32 % imm [31:0] $end
$var reg 1 & PCSrc $end
$var reg 1 ' clk $end
$var reg 32 ( instr [31:0] $end
$var reg 1 ) reset $end
$scope module branch_adder_inst $end
$var wire 32 * pc_branch [31:0] $end
$var wire 32 + pc [31:0] $end
$var wire 32 , imm [31:0] $end
$upscope $end
$scope module imm_gen_inst $end
$var wire 32 - instr [31:0] $end
$var wire 7 . opcode [6:0] $end
$var reg 32 / imm [31:0] $end
$upscope $end
$scope module pc_adder_inst $end
$var wire 32 0 pc_next_seq [31:0] $end
$var wire 32 1 pc [31:0] $end
$upscope $end
$scope module pc_inst $end
$var wire 1 ' clk $end
$var wire 1 ) reset $end
$var wire 32 2 pc_next [31:0] $end
$var reg 32 3 pc [31:0] $end
$upscope $end
$scope module pc_mux $end
$var wire 32 4 in0 [31:0] $end
$var wire 32 5 in1 [31:0] $end
$var wire 1 & sel $end
$var wire 32 6 out [31:0] $end
$var parameter 32 7 WIDTH $end
$upscope $end
$upscope $end
$enddefinitions $end
$comment Show the parameter values. $end
$dumpall
b100000 7
$end
#0
$dumpvars
b100 6
b0 5
b100 4
b0 3
b100 2
b0 1
b100 0
b0 /
b0 .
b0 -
b0 ,
b0 +
b0 *
1)
b0 (
0'
0&
b0 %
b0 $
b0 #
b100 "
b100 !
$end
#5
1'
#10
0'
0)
#15
b1000 "
b1000 2
b1000 6
b1000 !
b1000 0
b1000 4
b100 #
b100 *
b100 5
b100 $
b100 +
b100 1
b100 3
1'
#20
0'
#25
b1100 "
b1100 2
b1100 6
b1100 !
b1100 0
b1100 4
b1000 #
b1000 *
b1000 5
b1000 $
b1000 +
b1000 1
b1000 3
1'
#30
b0 #
b0 *
b0 5
b11111111111111111111111111111100 %
b11111111111111111111111111111100 ,
b11111111111111111111111111111100 /
b1100011 .
0'
b11111110001000001000110011100011 (
b11111110001000001000110011100011 -
#35
b10000 "
b10000 2
b10000 6
b10000 !
b10000 0
b10000 4
b100 #
b100 *
b100 5
b1100 $
b1100 +
b1100 1
b1100 3
1'
#40
b100 "
b100 2
b100 6
0'
1&
#45
b11111111111111111111111111111100 "
b11111111111111111111111111111100 2
b11111111111111111111111111111100 6
b1000 !
b1000 0
b1000 4
b11111111111111111111111111111100 #
b11111111111111111111111111111100 *
b11111111111111111111111111111100 5
b100 $
b100 +
b100 1
b100 3
1'
#50
b1000 "
b1000 2
b1000 6
0'
0&
#55
b1100 "
b1100 2
b1100 6
b1100 !
b1100 0
b1100 4
b0 #
b0 *
b0 5
b1000 $
b1000 +
b1000 1
b1000 3
1'
#60
b100110 #
b100110 *
b100110 5
b1111 %
b1111 ,
b1111 /
b10011 .
0'
b111100000000000010010011 (
b111100000000000010010011 -
#65
b10000 "
b10000 2
b10000 6
b10000 !
b10000 0
b10000 4
b101010 #
b101010 *
b101010 5
b1100 $
b1100 +
b1100 1
b1100 3
1'
